icamix/__init__.py
icamix/mix.py
icamix-0.6.dist-info/LICENSE
icamix-0.6.dist-info/METADATA
icamix-0.6.dist-info/WHEEL
icamix-0.6.dist-info/top_level.txt
icamix-0.6.dist-info/RECORD
