Metadata-Version: 2.1
Name: icamix
Version: 0.6
Summary: A package for amplitude mixing
Home-page: https://github.com/rqfzpy/icamix
Author: fzpy
Author-email: 690799557@qq.com
Classifier: Programming Language :: Python :: 3
License-File: LICENSE
Requires-Dist: torch
